ecscrape/__init__.py
ecscrape/lib.py
ecscrape/tools.py
ecscrape-0.0.2.dist-info/LICENSE
ecscrape-0.0.2.dist-info/METADATA
ecscrape-0.0.2.dist-info/WHEEL
ecscrape-0.0.2.dist-info/entry_points.txt
ecscrape-0.0.2.dist-info/RECORD
